sqlgrep/__init__.py
sqlgrep-0.0.14.dist-info/METADATA
sqlgrep-0.0.14.dist-info/WHEEL
sqlgrep-0.0.14.dist-info/entry_points.txt
sqlgrep-0.0.14.dist-info/licenses/LICENSE
sqlgrep-0.0.14.dist-info/RECORD
