Metadata-Version: 2.4
Name: sqlgrep
Version: 0.0.14
Summary: Find string anywhere in database
Project-URL: Homepage, https://github.com/yaroslaff/sqlgrep
Project-URL: Issues, https://github.com/yaroslaff/sqlgrep/issues
Author-email: Yaroslav Polyakov <yaroslaff@gmail.com>
License: MIT License
License-File: LICENSE
Classifier: License :: OSI Approved :: MIT License
Classifier: Operating System :: OS Independent
Classifier: Programming Language :: Python :: 3
Requires-Python: >=3.8
Requires-Dist: rich
Requires-Dist: sqlalchemy
Provides-Extra: mysql
Requires-Dist: mysqlclient; extra == 'mysql'
Provides-Extra: postgresql
Requires-Dist: psycopg2; extra == 'postgresql'
